rasp_util/__init__.py
rasp_util/auto_patch.py
RASP-1.0.0.dist-info/METADATA
RASP-1.0.0.dist-info/WHEEL
RASP-1.0.0.dist-info/top_level.txt
RASP-1.0.0.dist-info/RECORD
