Metadata-Version: 2.1
Name: RASP
Version: 1.0.0
Summary: Runtime application self-protection
Home-page: https://www.python.org/
License: UNKNOWN
Platform: UNKNOWN
Requires-Python: >=3
